{"id":"792D7DFAFAE2427BBE82BD72491D3D35","name":"MarienBurgerie","kind":"Imbissbetriebe einschl. mobile Einrichtung","address":"Marienburger Str. 47\n10405 Berlin","imageFiles":["BA98BDAAB14249E3925E26FDAB477E15.jpg","40FB1F865FC44D6BBEBEE46A1690D1FF.jpg","2ECBD811AEFF424888102F40DA8B8234.jpg","29B875125CAE4AC286D4BB2AAC3D12DE.jpg"],"results":{"date":"2022-02-07T00:00:00.000Z","points":"65\n64","conclusion":"gut\ngut","smiley":"gut"},"followUps":[],"details":[{"property":"Einhaltung LM-rechtlicher Bestimmungen","achievedPoints":"4","possiblePoints":"5"},{"property":"R체ckverfolgbarkeit","achievedPoints":"3","possiblePoints":"3"},{"property":"Mitarbeiterschulung","achievedPoints":"7","possiblePoints":"7"},{"property":"HACCP - Verfahren","achievedPoints":"12","possiblePoints":"12"},{"property":"Untersuchung von Produkten","achievedPoints":"4","possiblePoints":"5"},{"property":"Temperatureinhaltung (K체hlung)","achievedPoints":"8","possiblePoints":"8"},{"property":"Bauliche Beschaffenheit (Instandhaltung)","achievedPoints":"4","possiblePoints":"5"},{"property":"Reinigung und Desinfektion (R+D)","achievedPoints":"6","possiblePoints":"8"},{"property":"Personalhygiene","achievedPoints":"8","possiblePoints":"11"},{"property":"Produktionshygiene","achievedPoints":"6","possiblePoints":"13"},{"property":"Sch채dlingsbek채mpfung","achievedPoints":"3","possiblePoints":"3"}]}
