{"id":"8CE98F5A93D47D7AE0536884190A6865","name":"Inpastando","kind":"Speisegaststätte","address":"Langhansstr. 118\n13086 Berlin","imageFiles":["A43A5F4FD1CF4BBE8146FD6E20D5FA02.jpg","30F6809CE3434229BBB3A689C2B3075E.jpg","120C178E247D4AB1958195799C64EBCC.jpg","291ABA75FDCD44EE818940230B679E2A.jpg"],"results":{"date":"2022-06-29T00:00:00.000Z","points":"70","conclusion":"gut","smiley":"gut"},"followUps":[{"date":"2022-07-21T00:00:00.000Z","result":"Mängel überwiegend abgestellt"}],"details":[{"property":"Einhaltung LM-rechtlicher Bestimmungen","achievedPoints":"3","possiblePoints":"5"},{"property":"Rückverfolgbarkeit","achievedPoints":"3","possiblePoints":"3"},{"property":"Mitarbeiterschulung","achievedPoints":"7","possiblePoints":"7"},{"property":"HACCP - Verfahren","achievedPoints":"12","possiblePoints":"12"},{"property":"Untersuchung von Produkten","achievedPoints":"5","possiblePoints":"5"},{"property":"Temperatureinhaltung (Kühlung)","achievedPoints":"8","possiblePoints":"8"},{"property":"Bauliche Beschaffenheit (Instandhaltung)","achievedPoints":"3","possiblePoints":"5"},{"property":"Reinigung und Desinfektion (R+D)","achievedPoints":"6","possiblePoints":"8"},{"property":"Personalhygiene","achievedPoints":"11","possiblePoints":"11"},{"property":"Produktionshygiene","achievedPoints":"9","possiblePoints":"13"},{"property":"Schädlingsbekämpfung","achievedPoints":"3","possiblePoints":"3"}]}
