{"id":"6D6D81D23C3D4D298EF07F78A8EF76EF","name":"Bäckerei","kind":"Cafes/Milchbar/Eisdiele ohne eigene Herstellung","address":"Langhansstr. 18\n13086 Berlin","imageFiles":["582505C836E642E58B42EDEEBB1B881E.jpg","E8430B34A10A470ABF73B0511783E561.jpg","E20092EA1A4648878717ABBBCE493A59.jpg","6E4DDF80B2C74D1D9EA8645A5B73B39B.jpg"],"results":{"date":"2021-05-14T00:00:00.000Z","points":"57","conclusion":"zufriedenstellend","smiley":"befriedigend"},"followUps":[],"details":[{"property":"Einhaltung LM-rechtlicher Bestimmungen","achievedPoints":"4","possiblePoints":"5"},{"property":"Rückverfolgbarkeit","achievedPoints":"1","possiblePoints":"3"},{"property":"Mitarbeiterschulung","achievedPoints":"5","possiblePoints":"7"},{"property":"HACCP - Verfahren","achievedPoints":"9","possiblePoints":"12"},{"property":"Untersuchung von Produkten","achievedPoints":"4","possiblePoints":"5"},{"property":"Temperatureinhaltung (Kühlung)","achievedPoints":"6","possiblePoints":"8"},{"property":"Bauliche Beschaffenheit (Instandhaltung)","achievedPoints":"4","possiblePoints":"5"},{"property":"Reinigung und Desinfektion (R+D)","achievedPoints":"6","possiblePoints":"8"},{"property":"Personalhygiene","achievedPoints":"8","possiblePoints":"11"},{"property":"Produktionshygiene","achievedPoints":"9","possiblePoints":"13"},{"property":"Schädlingsbekämpfung","achievedPoints":"1","possiblePoints":"3"}]}
