{"id":"CB9593B1F69A46D9AEE2289A2EBA3DAC","name":"Hum-Vegan","kind":"Speisegaststätte","address":"Raumerstr. 38\n10437 Berlin","imageFiles":["07D2765662124152A98AD8A65C83E73B.jpg","A9E7B0AD9CDC45A185F77ED790A050F8.jpg","0BAFD3BD61AE46049BF8FEFF67E649C8.jpg","F8707448FA9344C08762ED21FD65D6EB.jpg"],"results":{"date":"2021-05-12T00:00:00.000Z","points":"27","conclusion":"ausreichend","smiley":"ausreichend"},"followUps":[{"date":"2021-05-27T00:00:00.000Z","result":"Mängel überwiegend abgestellt"}],"details":[{"property":"Einhaltung LM-rechtlicher Bestimmungen","achievedPoints":"3","possiblePoints":"5"},{"property":"Rückverfolgbarkeit","achievedPoints":"1","possiblePoints":"3"},{"property":"Mitarbeiterschulung","achievedPoints":"1","possiblePoints":"7"},{"property":"HACCP - Verfahren","achievedPoints":"3","possiblePoints":"12"},{"property":"Untersuchung von Produkten","achievedPoints":"3","possiblePoints":"5"},{"property":"Temperatureinhaltung (Kühlung)","achievedPoints":"4","possiblePoints":"8"},{"property":"Bauliche Beschaffenheit (Instandhaltung)","achievedPoints":"3","possiblePoints":"5"},{"property":"Reinigung und Desinfektion (R+D)","achievedPoints":"2","possiblePoints":"8"},{"property":"Personalhygiene","achievedPoints":"3","possiblePoints":"11"},{"property":"Produktionshygiene","achievedPoints":"3","possiblePoints":"13"},{"property":"Schädlingsbekämpfung","achievedPoints":"1","possiblePoints":"3"}]}
