{"id":"598EF5F0DA844AA68C655C0422D6E740","name":"Konditorei Krautzig","kind":"Konditorei","address":"Schönhauser Allee 126\n10437 Berlin","imageFiles":["946DE80AA6E74FF1BE4B3B3EAD2343CD.jpg","218E511F03BB443C91DE9C2FA0126C00.jpg","2DA6C12D6709414584B00E6CC111C5F9.jpg"],"results":{"date":"2022-03-21T00:00:00.000Z","points":"59","conclusion":"gut","smiley":"gut"},"followUps":[],"details":[{"property":"Einhaltung LM-rechtlicher Bestimmungen","achievedPoints":"3","possiblePoints":"5"},{"property":"Rückverfolgbarkeit","achievedPoints":"3","possiblePoints":"3"},{"property":"Mitarbeiterschulung","achievedPoints":"3","possiblePoints":"7"},{"property":"HACCP - Verfahren","achievedPoints":"9","possiblePoints":"12"},{"property":"Untersuchung von Produkten","achievedPoints":"3","possiblePoints":"5"},{"property":"Temperatureinhaltung (Kühlung)","achievedPoints":"8","possiblePoints":"8"},{"property":"Bauliche Beschaffenheit (Instandhaltung)","achievedPoints":"4","possiblePoints":"5"},{"property":"Reinigung und Desinfektion (R+D)","achievedPoints":"6","possiblePoints":"8"},{"property":"Personalhygiene","achievedPoints":"8","possiblePoints":"11"},{"property":"Produktionshygiene","achievedPoints":"9","possiblePoints":"13"},{"property":"Schädlingsbekämpfung","achievedPoints":"3","possiblePoints":"3"}]}
