{"id":"8E5DF6DC33EF4B788B3AA217EF970D89","name":"Tabak Presse BVG-Service Hermesshop","kind":"Kiosk/Mini-Markt","address":"Langhansstr. 117\n13086 Berlin","imageFiles":["1F2F3029CD444075AF17E3C206ACB6BB.jpg","4271881D1863420BBFD14C3A13F65DBA.jpg","03744F84F58B44FD85988011B9EFB52E.jpg"],"results":{"date":"2021-04-22T00:00:00.000Z","points":"74","conclusion":"gut","smiley":"gut"},"followUps":[],"details":[{"property":"Einhaltung LM-rechtlicher Bestimmungen","achievedPoints":"5","possiblePoints":"5"},{"property":"R체ckverfolgbarkeit","achievedPoints":"3","possiblePoints":"3"},{"property":"Mitarbeiterschulung","achievedPoints":"7","possiblePoints":"7"},{"property":"HACCP - Verfahren","achievedPoints":"9","possiblePoints":"12"},{"property":"Untersuchung von Produkten","achievedPoints":"5","possiblePoints":"5"},{"property":"Temperatureinhaltung (K체hlung)","achievedPoints":"8","possiblePoints":"8"},{"property":"Bauliche Beschaffenheit (Instandhaltung)","achievedPoints":"4","possiblePoints":"5"},{"property":"Reinigung und Desinfektion (R+D)","achievedPoints":"8","possiblePoints":"8"},{"property":"Personalhygiene","achievedPoints":"11","possiblePoints":"11"},{"property":"Produktionshygiene","achievedPoints":"13","possiblePoints":"13"},{"property":"Sch채dlingsbek채mpfung","achievedPoints":"1","possiblePoints":"3"}]}
