{"id":"66BA73A600922E00E0536884190A96D7","name":"Bella Venezia","kind":"Imbissbetriebe einschl. mobile Einrichtung","address":"Florastr. 32\n13187 Berlin","imageFiles":["8FAEC08B921C401BACD8D5CF5C8D8819.jpg","DEB2908C3278411DA2422714707AD772.jpg","7A8CD757C11D46EDB0E6A11878C813BB.jpg","ADB7689C75814FDDA46ECAE2D7ADD340.jpg"],"results":{"date":"2022-10-06T00:00:00.000Z","points":"1","conclusion":"nicht ausreichend","smiley":"nichtausreichend"},"followUps":[],"details":[{"property":"Einhaltung LM-rechtlicher Bestimmungen","achievedPoints":"0","possiblePoints":"5"},{"property":"R체ckverfolgbarkeit","achievedPoints":"0","possiblePoints":"3"},{"property":"Mitarbeiterschulung","achievedPoints":"0","possiblePoints":"7"},{"property":"HACCP - Verfahren","achievedPoints":"0","possiblePoints":"12"},{"property":"Untersuchung von Produkten","achievedPoints":"0","possiblePoints":"5"},{"property":"Temperatureinhaltung (K체hlung)","achievedPoints":"0","possiblePoints":"8"},{"property":"Bauliche Beschaffenheit (Instandhaltung)","achievedPoints":"0","possiblePoints":"5"},{"property":"Reinigung und Desinfektion (R+D)","achievedPoints":"0","possiblePoints":"8"},{"property":"Personalhygiene","achievedPoints":"0","possiblePoints":"11"},{"property":"Produktionshygiene","achievedPoints":"0","possiblePoints":"13"},{"property":"Sch채dlingsbek채mpfung","achievedPoints":"1","possiblePoints":"3"}]}
