{"id":"2C3FDF691A2348628C1ACE8556BC40C5","name":"Brotmeisterei Steinecke","kind":"Bäckereifiliale und (eigenständige) -verkaufsabteilung","address":"Pasewalker Str. 115\n13127 Berlin","imageFiles":["4C580B33FEFB49FFADA71AB0867A560F.jpg","2652DAEC688B456EA6BA8BC90513FE92.jpg","13DE8AF1E1BB4F8F928092E8229B0622.jpg","F74B795B89594E379FF81B2CFB10E9E0.jpg"],"results":{"date":"2021-11-29T00:00:00.000Z","points":"72","conclusion":"gut","smiley":"gut"},"followUps":[],"details":[{"property":"Einhaltung LM-rechtlicher Bestimmungen","achievedPoints":"5","possiblePoints":"5"},{"property":"Rückverfolgbarkeit","achievedPoints":"3","possiblePoints":"3"},{"property":"Mitarbeiterschulung","achievedPoints":"7","possiblePoints":"7"},{"property":"HACCP - Verfahren","achievedPoints":"12","possiblePoints":"12"},{"property":"Untersuchung von Produkten","achievedPoints":"5","possiblePoints":"5"},{"property":"Temperatureinhaltung (Kühlung)","achievedPoints":"8","possiblePoints":"8"},{"property":"Bauliche Beschaffenheit (Instandhaltung)","achievedPoints":"3","possiblePoints":"5"},{"property":"Reinigung und Desinfektion (R+D)","achievedPoints":"6","possiblePoints":"8"},{"property":"Personalhygiene","achievedPoints":"11","possiblePoints":"11"},{"property":"Produktionshygiene","achievedPoints":"9","possiblePoints":"13"},{"property":"Schädlingsbekämpfung","achievedPoints":"3","possiblePoints":"3"}]}
