{"id":"05B835B357FC4F619484B8A302EDD70C","name":"Mrs. Robinson`s","kind":"Speisegaststätte","address":"Pappelallee 29\n10437 Berlin","imageFiles":["EBCB107A6487456FBBA917A318CDB48B.jpg","C39F7E736AC44BDBAF57A0C969504C36.jpg","F1BFF4668CA14175A008F42C193A5E20.jpg","04D0E32043F5415D9E82F9B8BA62578A.jpg"],"results":{"date":"2022-03-31T00:00:00.000Z","points":"44","conclusion":"zufriedenstellend","smiley":"befriedigend"},"followUps":[{"date":"2022-06-28T00:00:00.000Z","result":"Mängel überwiegend abgestellt"}],"details":[{"property":"Einhaltung LM-rechtlicher Bestimmungen","achievedPoints":"3","possiblePoints":"5"},{"property":"Rückverfolgbarkeit","achievedPoints":"3","possiblePoints":"3"},{"property":"Mitarbeiterschulung","achievedPoints":"3","possiblePoints":"7"},{"property":"HACCP - Verfahren","achievedPoints":"6","possiblePoints":"12"},{"property":"Untersuchung von Produkten","achievedPoints":"4","possiblePoints":"5"},{"property":"Temperatureinhaltung (Kühlung)","achievedPoints":"8","possiblePoints":"8"},{"property":"Bauliche Beschaffenheit (Instandhaltung)","achievedPoints":"3","possiblePoints":"5"},{"property":"Reinigung und Desinfektion (R+D)","achievedPoints":"2","possiblePoints":"8"},{"property":"Personalhygiene","achievedPoints":"6","possiblePoints":"11"},{"property":"Produktionshygiene","achievedPoints":"3","possiblePoints":"13"},{"property":"Schädlingsbekämpfung","achievedPoints":"3","possiblePoints":"3"}]}
