{"id":"2E735775557A497695C89B9910C4908F","name":"Palermo","kind":"Speisegaststätte","address":"Falkenberger Str. 160\n13088 Berlin","imageFiles":["FA3DE5F308E84111B4DB5089DABD3A37.jpg","666EE125C4544610ACA336E7ED6EABC5.jpg","888F5BBB90714ACCAFD27F41C1E99F90.jpg"],"results":{"date":"2022-07-19T00:00:00.000Z","points":"38\n70","conclusion":"ausreichend\ngut","smiley":"ausreichend"},"followUps":[],"details":[{"property":"Einhaltung LM-rechtlicher Bestimmungen","achievedPoints":"3","possiblePoints":"5"},{"property":"Rückverfolgbarkeit","achievedPoints":"0","possiblePoints":"3"},{"property":"Mitarbeiterschulung","achievedPoints":"7","possiblePoints":"7"},{"property":"HACCP - Verfahren","achievedPoints":"0","possiblePoints":"12"},{"property":"Untersuchung von Produkten","achievedPoints":"2","possiblePoints":"5"},{"property":"Temperatureinhaltung (Kühlung)","achievedPoints":"4","possiblePoints":"8"},{"property":"Bauliche Beschaffenheit (Instandhaltung)","achievedPoints":"3","possiblePoints":"5"},{"property":"Reinigung und Desinfektion (R+D)","achievedPoints":"4","possiblePoints":"8"},{"property":"Personalhygiene","achievedPoints":"6","possiblePoints":"11"},{"property":"Produktionshygiene","achievedPoints":"9","possiblePoints":"13"},{"property":"Schädlingsbekämpfung","achievedPoints":"0","possiblePoints":"3"}]}
