{"id":"A8D25EED52D54C22BBD5D9F74E2ADCC2","name":"Kita - Kita Toblacher","kind":"Essenausgabestelle","address":"Toblacher Str. 42\n13189 Berlin","imageFiles":["59116FBE2FCA46729DCF6781FB6D1B0E.jpg","48B42D783C3C47468BB38A5B3615D720.jpg","0A001002607045E0971B4A990F463D7A.jpg","6D9C60BD5DA84083B7F69074F864B2A7.jpg"],"results":{"date":"2020-12-09T00:00:00.000Z","points":"60","conclusion":"gut","smiley":"gut"},"followUps":[],"details":[{"property":"Einhaltung LM-rechtlicher Bestimmungen","achievedPoints":"5","possiblePoints":"5"},{"property":"R체ckverfolgbarkeit","achievedPoints":"1","possiblePoints":"3"},{"property":"Mitarbeiterschulung","achievedPoints":"7","possiblePoints":"7"},{"property":"HACCP - Verfahren","achievedPoints":"9","possiblePoints":"12"},{"property":"Untersuchung von Produkten","achievedPoints":"3","possiblePoints":"5"},{"property":"Temperatureinhaltung (K체hlung)","achievedPoints":"8","possiblePoints":"8"},{"property":"Bauliche Beschaffenheit (Instandhaltung)","achievedPoints":"3","possiblePoints":"5"},{"property":"Reinigung und Desinfektion (R+D)","achievedPoints":"4","possiblePoints":"8"},{"property":"Personalhygiene","achievedPoints":"8","possiblePoints":"11"},{"property":"Produktionshygiene","achievedPoints":"9","possiblePoints":"13"},{"property":"Sch채dlingsbek채mpfung","achievedPoints":"3","possiblePoints":"3"}]}
