{"id":"66CED98AA4347EA9E0536884190AB2B4","name":"Funa Sushi Lieferservice","kind":"Verpflegungsdienst Bringdienst","address":"Prenzlauer Promenade 12\n13086 Berlin","imageFiles":["5D26AB15E19E465DB90060640769F834.jpg","5BE1F6EF65174A88A94E4272CB8F68FF.jpg","019C5FC442DC4523902434E003F86AC5.jpg","E28F845B9F7246468CD38BF297FC6906.jpg"],"results":{"date":"2022-03-16T00:00:00.000Z","points":"43\n29","conclusion":"zufriedenstellend\nausreichend","smiley":"befriedigend"},"followUps":[{"date":"2022-03-28T00:00:00.000Z","result":"Mängel teilweise abgestellt"}],"details":[{"property":"Einhaltung LM-rechtlicher Bestimmungen","achievedPoints":"3","possiblePoints":"5"},{"property":"Rückverfolgbarkeit","achievedPoints":"1","possiblePoints":"3"},{"property":"Mitarbeiterschulung","achievedPoints":"3","possiblePoints":"7"},{"property":"HACCP - Verfahren","achievedPoints":"6","possiblePoints":"12"},{"property":"Untersuchung von Produkten","achievedPoints":"4","possiblePoints":"5"},{"property":"Temperatureinhaltung (Kühlung)","achievedPoints":"6","possiblePoints":"8"},{"property":"Bauliche Beschaffenheit (Instandhaltung)","achievedPoints":"3","possiblePoints":"5"},{"property":"Reinigung und Desinfektion (R+D)","achievedPoints":"4","possiblePoints":"8"},{"property":"Personalhygiene","achievedPoints":"6","possiblePoints":"11"},{"property":"Produktionshygiene","achievedPoints":"6","possiblePoints":"13"},{"property":"Schädlingsbekämpfung","achievedPoints":"1","possiblePoints":"3"}]}
