{"id":"BC0F37664EAB7F5FE0536884190AC66F","name":"Frank Café","kind":"Cafes/Milchbar/Eisdiele ohne eigene Herstellung","address":"Schönhauser Allee 176\n10119 Berlin","imageFiles":["CB1705EB800E4B0BBBC038F0E7796319.jpg","7BC1ECBD9F6643B3969E3629E4EC4CC1.jpg","142B782DD94A46C7B0A690DABACE6055.jpg"],"results":{"date":"2022-05-31T00:00:00.000Z","points":"72","conclusion":"gut","smiley":"gut"},"followUps":[],"details":[{"property":"Einhaltung LM-rechtlicher Bestimmungen","achievedPoints":"4","possiblePoints":"5"},{"property":"Rückverfolgbarkeit","achievedPoints":"3","possiblePoints":"3"},{"property":"Mitarbeiterschulung","achievedPoints":"7","possiblePoints":"7"},{"property":"HACCP - Verfahren","achievedPoints":"12","possiblePoints":"12"},{"property":"Untersuchung von Produkten","achievedPoints":"5","possiblePoints":"5"},{"property":"Temperatureinhaltung (Kühlung)","achievedPoints":"8","possiblePoints":"8"},{"property":"Bauliche Beschaffenheit (Instandhaltung)","achievedPoints":"5","possiblePoints":"5"},{"property":"Reinigung und Desinfektion (R+D)","achievedPoints":"6","possiblePoints":"8"},{"property":"Personalhygiene","achievedPoints":"6","possiblePoints":"11"},{"property":"Produktionshygiene","achievedPoints":"13","possiblePoints":"13"},{"property":"Schädlingsbekämpfung","achievedPoints":"3","possiblePoints":"3"}]}
