{"id":"AA741CCC7DD8271AE0536884190A7ECC","name":"Back & Snack","kind":"Bäckereifiliale und (eigenständige) -verkaufsabteilung","address":"Birnbaumring 92\n13159 Berlin","imageFiles":["CA9726125AF04746AC771BAF34EC5125.jpg","2ACB11ECA8164F81BD2256587A7886DA.jpg","5775811FA13E4B66A6ECFAA43FF0CAFF.jpg","8A37D95E94E34EBFB62193D6F020D6B5.jpg"],"results":{"date":"2021-04-27T00:00:00.000Z","points":"22","conclusion":"ausreichend","smiley":"ausreichend"},"followUps":[{"date":"2021-05-20T00:00:00.000Z","result":"Mängel überwiegend abgestellt"}],"details":[{"property":"Einhaltung LM-rechtlicher Bestimmungen","achievedPoints":"5","possiblePoints":"5"},{"property":"Rückverfolgbarkeit","achievedPoints":"1","possiblePoints":"3"},{"property":"Mitarbeiterschulung","achievedPoints":"0","possiblePoints":"7"},{"property":"HACCP - Verfahren","achievedPoints":"0","possiblePoints":"12"},{"property":"Untersuchung von Produkten","achievedPoints":"3","possiblePoints":"5"},{"property":"Temperatureinhaltung (Kühlung)","achievedPoints":"0","possiblePoints":"8"},{"property":"Bauliche Beschaffenheit (Instandhaltung)","achievedPoints":"2","possiblePoints":"5"},{"property":"Reinigung und Desinfektion (R+D)","achievedPoints":"4","possiblePoints":"8"},{"property":"Personalhygiene","achievedPoints":"3","possiblePoints":"11"},{"property":"Produktionshygiene","achievedPoints":"3","possiblePoints":"13"},{"property":"Schädlingsbekämpfung","achievedPoints":"1","possiblePoints":"3"}]}
