{"id":"E041AFC7F07946D1821AFF5EB8810DCF","name":"Boulangerie","kind":"Bäckereifiliale und (eigenständige) -verkaufsabteilung","address":"Lettestr. 1\n10437 Berlin","imageFiles":["817CCD5513FD46A7893A9B0BC46B639E.jpg","5F4B3D48A84A4CE88CE3DDFCC6F50D4A.jpg","9F577B096B074AE0B4021CEC8C22440D.jpg","0C5053CDBAED470489B888A3396A7718.jpg"],"results":{"date":"2022-02-02T00:00:00.000Z","points":"23","conclusion":"ausreichend","smiley":"ausreichend"},"followUps":[{"date":"2022-02-22T00:00:00.000Z","result":"Mängel teilweise abgestellt"}],"details":[{"property":"Einhaltung LM-rechtlicher Bestimmungen","achievedPoints":"2","possiblePoints":"5"},{"property":"Rückverfolgbarkeit","achievedPoints":"1","possiblePoints":"3"},{"property":"Mitarbeiterschulung","achievedPoints":"1","possiblePoints":"7"},{"property":"HACCP - Verfahren","achievedPoints":"3","possiblePoints":"12"},{"property":"Untersuchung von Produkten","achievedPoints":"3","possiblePoints":"5"},{"property":"Temperatureinhaltung (Kühlung)","achievedPoints":"2","possiblePoints":"8"},{"property":"Bauliche Beschaffenheit (Instandhaltung)","achievedPoints":"2","possiblePoints":"5"},{"property":"Reinigung und Desinfektion (R+D)","achievedPoints":"2","possiblePoints":"8"},{"property":"Personalhygiene","achievedPoints":"3","possiblePoints":"11"},{"property":"Produktionshygiene","achievedPoints":"3","possiblePoints":"13"},{"property":"Schädlingsbekämpfung","achievedPoints":"1","possiblePoints":"3"}]}
