{"id":"71CF20BCF48B633EE0536884190A22BF","name":"Lebensmittel und Getränke","kind":"Kiosk/Mini-Markt","address":"Schönfließer Str. 10\n10439 Berlin","imageFiles":["4AC544B5BE02427EAE7401B9C844FC29.jpg","8459AEB194474C7CA41223BFAD154370.jpg","7AF7642CCD434A4CAD5A1A97630BE578.jpg","99E9DB065FB7493E9181F4692831E47C.jpg"],"results":{"date":"2021-04-08T00:00:00.000Z","points":"23","conclusion":"ausreichend","smiley":"ausreichend"},"followUps":[{"date":"2021-04-22T00:00:00.000Z","result":"Mängel überwiegend abgestellt"}],"details":[{"property":"Einhaltung LM-rechtlicher Bestimmungen","achievedPoints":"4","possiblePoints":"5"},{"property":"Rückverfolgbarkeit","achievedPoints":"1","possiblePoints":"3"},{"property":"Mitarbeiterschulung","achievedPoints":"1","possiblePoints":"7"},{"property":"HACCP - Verfahren","achievedPoints":"3","possiblePoints":"12"},{"property":"Untersuchung von Produkten","achievedPoints":"2","possiblePoints":"5"},{"property":"Temperatureinhaltung (Kühlung)","achievedPoints":"2","possiblePoints":"8"},{"property":"Bauliche Beschaffenheit (Instandhaltung)","achievedPoints":"2","possiblePoints":"5"},{"property":"Reinigung und Desinfektion (R+D)","achievedPoints":"4","possiblePoints":"8"},{"property":"Personalhygiene","achievedPoints":"0","possiblePoints":"11"},{"property":"Produktionshygiene","achievedPoints":"3","possiblePoints":"13"},{"property":"Schädlingsbekämpfung","achievedPoints":"1","possiblePoints":"3"}]}
