{"id":"87422531F2840EF1E0536884190AC232","name":"Burgermeister","kind":"Imbissbetriebe einschl. mobile Einrichtung","address":"Schönhauser Allee 45\n10435 Berlin","imageFiles":["4BD087DF73294085A97AEADD260ACFFE.jpg","1BCE050DC3D9464998CF584F92AF77B9.jpg","BA3CAD78BE6C4EE299EB6FCFC8299650.jpg","33E555E6346B4D799E50C16A9DA02379.jpg"],"results":{"date":"2022-03-15T00:00:00.000Z","points":"62","conclusion":"gut","smiley":"gut"},"followUps":[],"details":[{"property":"Einhaltung LM-rechtlicher Bestimmungen","achievedPoints":"4","possiblePoints":"5"},{"property":"Rückverfolgbarkeit","achievedPoints":"3","possiblePoints":"3"},{"property":"Mitarbeiterschulung","achievedPoints":"7","possiblePoints":"7"},{"property":"HACCP - Verfahren","achievedPoints":"9","possiblePoints":"12"},{"property":"Untersuchung von Produkten","achievedPoints":"4","possiblePoints":"5"},{"property":"Temperatureinhaltung (Kühlung)","achievedPoints":"8","possiblePoints":"8"},{"property":"Bauliche Beschaffenheit (Instandhaltung)","achievedPoints":"3","possiblePoints":"5"},{"property":"Reinigung und Desinfektion (R+D)","achievedPoints":"6","possiblePoints":"8"},{"property":"Personalhygiene","achievedPoints":"8","possiblePoints":"11"},{"property":"Produktionshygiene","achievedPoints":"9","possiblePoints":"13"},{"property":"Schädlingsbekämpfung","achievedPoints":"1","possiblePoints":"3"}]}
