{"id":"30EEA788E3FD421E937CDB29D568A527","name":"Charme - Thai Bistro Café","kind":"Speisegaststätte","address":"Lychener Str. 13\n10437 Berlin","imageFiles":["4B34E5A5F7734B9BB05044768D842E12.jpg","454C8E61A73343E081A662CA166E4A3F.jpg","43C624A3A8684594B5542F2E6BC224FF.jpg","326B18EBCA3F473BBF868A41729678F7.jpg"],"results":{"date":"2022-02-15T00:00:00.000Z","points":"36","conclusion":"ausreichend","smiley":"ausreichend"},"followUps":[{"date":"2022-02-28T00:00:00.000Z","result":"Mängel überwiegend abgestellt"}],"details":[{"property":"Einhaltung LM-rechtlicher Bestimmungen","achievedPoints":"3","possiblePoints":"5"},{"property":"Rückverfolgbarkeit","achievedPoints":"3","possiblePoints":"3"},{"property":"Mitarbeiterschulung","achievedPoints":"3","possiblePoints":"7"},{"property":"HACCP - Verfahren","achievedPoints":"3","possiblePoints":"12"},{"property":"Untersuchung von Produkten","achievedPoints":"4","possiblePoints":"5"},{"property":"Temperatureinhaltung (Kühlung)","achievedPoints":"2","possiblePoints":"8"},{"property":"Bauliche Beschaffenheit (Instandhaltung)","achievedPoints":"4","possiblePoints":"5"},{"property":"Reinigung und Desinfektion (R+D)","achievedPoints":"4","possiblePoints":"8"},{"property":"Personalhygiene","achievedPoints":"6","possiblePoints":"11"},{"property":"Produktionshygiene","achievedPoints":"3","possiblePoints":"13"},{"property":"Schädlingsbekämpfung","achievedPoints":"1","possiblePoints":"3"}]}
