{"id":"73CD0862FFEF4BE18DADB7674DDA5104","name":"Schule am Birkenhof - Essenausgabe","kind":"Essenausgabestelle","address":"Arnouxstr. 18\n13127 Berlin","imageFiles":["22C8D4C5725A417487257B45D1349E62.jpg","216DAAEE82E145DCBF9850ABC8826A3D.jpg","E5BF994E52344E59A66E9E3327F6F633.jpg"],"results":{"date":"2021-12-17T00:00:00.000Z","points":"67","conclusion":"gut","smiley":"gut"},"followUps":[],"details":[{"property":"Einhaltung LM-rechtlicher Bestimmungen","achievedPoints":"5","possiblePoints":"5"},{"property":"R체ckverfolgbarkeit","achievedPoints":"3","possiblePoints":"3"},{"property":"Mitarbeiterschulung","achievedPoints":"7","possiblePoints":"7"},{"property":"HACCP - Verfahren","achievedPoints":"12","possiblePoints":"12"},{"property":"Untersuchung von Produkten","achievedPoints":"5","possiblePoints":"5"},{"property":"Temperatureinhaltung (K체hlung)","achievedPoints":"8","possiblePoints":"8"},{"property":"Bauliche Beschaffenheit (Instandhaltung)","achievedPoints":"3","possiblePoints":"5"},{"property":"Reinigung und Desinfektion (R+D)","achievedPoints":"6","possiblePoints":"8"},{"property":"Personalhygiene","achievedPoints":"6","possiblePoints":"11"},{"property":"Produktionshygiene","achievedPoints":"9","possiblePoints":"13"},{"property":"Sch채dlingsbek채mpfung","achievedPoints":"3","possiblePoints":"3"}]}
